imdiff/__init__.py
imdiff/__main__.py
imdiff/directory_comparator.py
imdiff/image_comparator.py
imdiff/list_files.py
imdiff/util.py
imdiff/version.py
imdiff/cli/__init__.py
imdiff/cli/dir_diff.py
imdiff/cli/image_diff.py
imdiff/cli/main.py
imdiff/gui/__init__.py
imdiff/gui/dir_diff_main_window.py
imdiff/gui/file_list_frame.py
imdiff/gui/image_canvas.py
imdiff/gui/image_diff_main_window.py
imdiff/gui/image_frame.py
imdiff/gui/image_scaling.py
imdiff/gui/status_bar.py
imdiff/gui/transient_menu.py
imdiff/gui/zoom_menu.py
imdiff-0.4.6.dist-info/licenses/LICENSE
imdiff-0.4.6.dist-info/METADATA
imdiff-0.4.6.dist-info/WHEEL
imdiff-0.4.6.dist-info/entry_points.txt
imdiff-0.4.6.dist-info/top_level.txt
imdiff-0.4.6.dist-info/RECORD
